cade_task/__init__.py
cade_task/__main__.py
cade_task/cli.py
cade_task/lib.py
cade_task-0.4.2.dist-info/LICENSE
cade_task-0.4.2.dist-info/METADATA
cade_task-0.4.2.dist-info/WHEEL
cade_task-0.4.2.dist-info/entry_points.txt
cade_task-0.4.2.dist-info/RECORD
