Metadata-Version: 2.1
Name: cade-task
Version: 0.4.2
Summary: A loose wrapper around reminders-cli
Author: Cade Ekblad-Frank
Author-email: cade@e-f.me
Requires-Python: >=3.11,<4.0
Classifier: Programming Language :: Python :: 3
Classifier: Programming Language :: Python :: 3.11
Requires-Dist: typer[all] (>=0.9.0,<0.10.0)
Project-URL: Homepage, https://github.com/cadeef/cade-task
